aliyun_mns_sdk-1.3.0.data/scripts/mnscmd
mns/__init__.py
mns/account.py
mns/auth.py
mns/message_property.py
mns/mns_client.py
mns/mns_common.py
mns/mns_exception.py
mns/mns_http.py
mns/mns_request.py
mns/mns_tool.py
mns/mns_xml_handler.py
mns/pkg_info.py
mns/queue.py
mns/subscription.py
mns/topic.py
aliyun_mns_sdk-1.3.0.dist-info/LICENSE
aliyun_mns_sdk-1.3.0.dist-info/METADATA
aliyun_mns_sdk-1.3.0.dist-info/WHEEL
aliyun_mns_sdk-1.3.0.dist-info/top_level.txt
aliyun_mns_sdk-1.3.0.dist-info/RECORD
