Metadata-Version: 2.1
Name: aliyun-mns-sdk
Version: 1.3.0
Summary: Aliyun Message Service Library
Home-page: 
Author: Aliyun MNS
Author-email: 
License: MIT
License-File: LICENSE
Requires-Dist: deprecated
Requires-Dist: pycryptodome
